Lab 05/part 04/cpu.v
/*          MUX UNIT
/*********************************************************************************************/

module MUX8(out,a,b,control);      //two input mux
	input [7:0] a;
	input [7:0] b;
	output [7:0] out;
	input control;
	reg [7:0] out;

	always@(a,b,control)begin       //  if inputs change this block run
		case(control)
			1'b0 : out=a[7:0];
			1'b1 : out=b[7:0];
		endcase
	end
endmodule

/*        32 BIT  MUX UNIT  working with timing
/*********************************************************************************************/

module MUX32(out,a,b,control,reset,clk);      //two input mux
	input [31:0] a;
    input reset,clk;
	input [31:0] b;
	output  [31:0] out;
	input control;
	reg [31:0] out;

	always@(a or posedge clk or posedge reset)begin       //  Here if input1 ,fall of clk,rice of reset should be out update

        if(reset==1)begin
            out=32'd0;
        end else if (control==1'b0) begin
            out=a[31:0];
        end else if(control==1'b1) begin
            out=b[31:0];
        end
	end

endmodule

/*         PC and 32 bit  MUX UNIT working with timing
/*********************************************************************************************/

module PC_MUX32(out,input1,input2,control,reset,clk);      //
	input [31:0] input1;
    input reset,clk;
	input [31:0] input2;
	output  [31:0] out;
	input control;
	reg [31:0] out;

	always@(input1  or posedge clk or posedge reset)begin       //  Here if input1 ,fall of clk,rice of reset should be out update

        #1                         // this delay for PC updateing
        if(reset==1)begin        // this start the program or giving the value for pc
            out=32'd0;
        end else if (control==1'b0) begin     // here to end mux function
            out=input1[31:0];
        end else if(control==1'b1) begin
            out=input2[31:0];            // if it is jump
        end
	end

endmodule



/*            2'S COMPLIMENT UNIT
/*********************************************************************************************/

module compliment(out,in);          // 2's compliment converter
    output [7:0] out;
    input [7:0] in;
    reg [7:0] comp=8'b11111111;
    assign #1 out=(comp-in)+8'b00000001; // math for converting
endmodule

// /*                    DEFAULT PROGRAM COUNTER UNIT
// /*********************************************************************************************/
 module counter (in_pc,out_pc,clk,reset);          //program counter unit

    input [31:0] in_pc;
    input clk,reset;
    output reg [31:0] out_pc;
    always @(posedge clk) begin   // this block always adding +4 with current pc value  in fall clk time
           out_pc=in_pc+32'd4;
    end

 endmodule

//                         Sing Extend and Shift unit
/*********************************************************************************************/

module sing_extend_shift(IN,OUT);
    input [7:0] IN;           // 8 bit immediate value as input
    output  [31:0] OUT;     // 32 bit output value for pc
    reg [31:0] result;
    assign OUT=result;
   always @(IN) begin // If IN change this will run
       #2 case(IN[7])   // most signifigent bit of input diside whether is this positive or negative
        1'b1:result<={22'b1111111111111111111111,IN,2'b00};   // if it is a negative value then sing extention
        1'b0:result<={22'b0000000000000000000000,IN,2'b00};    // if it is a positive value then sing extention
    endcase

   end

endmodule


    /*              CPU UNIT
    /*********************************************************************************************/


module cpu(PC, INSTRUCTION, CLK, RESET);
    output  [31:0]  PC;
    input CLK,RESET;
    input  [31:0] INSTRUCTION;

    wire [2:0] READREG1,READREG2,WRITEREG,OP_CODE;          // instruction decoding data addreses for sub module so those are wires

    reg WRITEENABLE,MUX1_SEL,MUX2_SEL,MUX4_SEL,JUMP,BEQ;                // reg file write enable signal and two muxes control signals

    reg [2:0] ALUOP,OP1,OP2,DESTINATION;         // instruction decoding data addreses for combinational logic  so those are reg

    reg [7:0] IM_VAL;    // this wire for geting immdeate

    wire MUX3_SEL;       // this for beq and defulte pc selection wire
    wire [31:0] Branch;    // this wire holding value of jump or value of beq  for pc updating
    assign Branch=NEXT+SinEx;        // this the adder operation so that for 2 time unit delay
    assign MUX3_SEL=BEQ & zero;          // selecting signal genetion for beq
    assign  PC=J_out;            // here assinnig output of jump mux value as pc

    assign  READREG2=INSTRUCTION[2:0];         // assing wire ports to  whenever change regaddres will get updates

    assign  READREG1=INSTRUCTION[10:8];


    assign  OP_CODE=INSTRUCTION[26:24];
    assign WRITEREG=DESTINATION;

    always @(*)
        begin
            if (OP_CODE==4'b0000) begin                              // assing wire ports to  whenever change regaddres will get updates
                DESTINATION=INSTRUCTION[18:16];
            end else begin
                DESTINATION=INSTRUCTION[18:16];
            end
                                 // Instruction Decode delay is added here because while decodeing only op_code get updated
            case(OP_CODE)
            4'b0000:   begin    // loadi  function combinational logic
                        WRITEENABLE=#1 1;
                        MUX2_SEL=1'b0;
                        ALUOP= 3'b000;
                        IM_VAL=INSTRUCTION[7:0];
                        BEQ=1'd0;
                        JUMP=1'd0;
                    end
            4'b0001:  begin     // move function combinational logic
                        WRITEENABLE=#1 1;
                        MUX1_SEL=1'b0;
                        MUX2_SEL=1'b1;
                        ALUOP= 3'b000;
                        BEQ=1'd0;
                        JUMP=1'd0;
                        IM_VAL=8'd0;

                    end
            4'b0010:  begin      //add function combinational logic
                        WRITEENABLE=#1 1;
                        MUX1_SEL=1'b0;
                        MUX2_SEL=1'b1;
                        ALUOP= 3'b001;
                        IM_VAL=8'd0;
                        BEQ=1'd0;
                        JUMP=1'd0;

                    end
            4'b0011:   begin     // sub function combinational logic
                        WRITEENABLE=#1 1;
                        MUX1_SEL=1'b1;
                        MUX2_SEL=1'b1;
                        ALUOP= 3'b001;
                        BEQ=1'd0;
                        JUMP=1'd0;
                        IM_VAL=8'd0;

                    end
            4'b0100:  begin       // And function combinational logic
                        WRITEENABLE=#1 1;
                        MUX1_SEL=1'b0;
                        MUX2_SEL=1'b1;
                        ALUOP= 3'b010;
                        BEQ=1'd0;
                        JUMP=1'd0;
                        IM_VAL=8'd0;

                    end
            4'b0101:  begin       //OR function combinational logic
                        WRITEENABLE=#1 1;
                        MUX1_SEL=1'b0;
                        MUX2_SEL=1'b1;
                        ALUOP= 3'b011;
                        BEQ=1'd0;
                        JUMP=1'd0;
                        IM_VAL=8'd0;

                    end
            4'b0110:  begin       //J function combinational logic
                        WRITEENABLE=#2 0;
                        BEQ=1'd0;
                        JUMP=1'd1;
                        IM_VAL=INSTRUCTION[23:16];

                    end
            4'b0111:  begin       //beq function combinational logic
                        WRITEENABLE=#2 0;
                        MUX1_SEL=1'b1;
                        MUX2_SEL=1'b1;
                        ALUOP= 3'b001;
                        BEQ=1'd1;
                        JUMP=1'd0;
                        IM_VAL=INSTRUCTION[23:16];

                    end
            endcase
        end


        //...........submodule connections  ............///


    //reg_file (IN, OUT1, OUT2, INADDRESS, OUT1ADDRESS, OUT2ADDRESS, WRITE, CLK, RESET);
    wire [7:0] IN;
    wire [7:0] OUT1;
    wire [7:0] OUT2;
    reg_file cpu_reg_file(IN,OUT1,OUT2,WRITEREG,READREG1,READREG2,WRITEENABLE,CLK,RESET);

    //module compliment(out,in);
    wire [7:0] OUT3;
    compliment cpu_compliment(OUT3,OUT2);       // get compliment value of out2

    //module MUX8(out,a,b,control);
    wire [7:0] OUT4;
    MUX8 cpu_MUX1(OUT4,OUT2,OUT3,MUX1_SEL);     // select compliment or normal value to out4

    //module MUX8(out,a,b,control);
    wire [7:0] OUT5;
    MUX8 cpu_MUX2(OUT5,IM_VAL,OUT4,MUX2_SEL);   // take immediate or reg value to out5

    //module alu(DATA1, DATA2, RESULT, SELECT);
    wire zero;
    alu cpu_alu(OUT1,OUT5,IN,ALUOP,zero);       // get alu output

    // module counter (in_pc,out_pc,clk,reset);
    wire [31:0]NEXT;
    wire [31:0] J_out;
    counter cpu_counter(J_out,NEXT,CLK,RESET);   // increase pc value

    //module sing_extend_shift(IN,OUT);
    wire [31:0]SinEx;
    sing_extend_shift cpu_sing_extend_shift(IM_VAL,SinEx); // change immdeate value for j and beq fucntion as 32 bit

    //module MUX32(out,a,b,control,reset,clk);
    wire [31:0] B_out;
    MUX32 cpu_MUX32_1(B_out,NEXT,Branch,MUX3_SEL,RESET,CLK);// Branch=NEXT+SinEx; MUX3_SEL=BEQ & ZERO
    // select Branch pc value or next pc value for beq

    //module PC_MUX32(out,a,b,control,reset,clk);

    PC_MUX32  cpu_PC_MUX32 (J_out,B_out,Branch,JUMP,RESET,CLK);// Branch=NEXT+SinEx; MUX3_SEL=BEQ & ZERO
    // select Branch pc value or next pc value for jump
endmodule

Lab 05/part 04/alu.v
// alu operations
module alu(DATA1, DATA2, RESULT, SELECT,ZERO);    // alu module
   input [7:0] DATA1,DATA2;                  // input datas
   output [7:0] RESULT;                      // output vaule
   input [2:0] SELECT;                       // operation
   output ZERO;
   wire [7:0]output_add,output_and,output_or,output_forward;  // save values from operations

   assign ZERO=(~(RESULT[0] | RESULT[1] | RESULT[2] | RESULT[3] | RESULT[4] | RESULT[5] | RESULT[6] | RESULT[7]));       // this doing the XOR operation if All bits are zero then its give 1 as out put otherwise 0 is output
   
   addope add1(DATA1,DATA2,output_add);    // call add function
   andope and1(DATA1,DATA2,output_and);    // call and fucntion
   orope or1(DATA1,DATA2,output_or);       // cal  or  fucntion
   forwardope forward1(DATA2,output_forward);  // call forward fucntion
   mux8_1 mux1(output_add,output_and,output_or,output_forward,SELECT,RESULT);  // call  mux functkon

endmodule //alu

//=========================================================mux
module mux8_1 (output_add,output_and,output_or,output_forward,SELECT,RESULT);
   input [7:0]output_add,output_and,output_or,output_forward;  // 4 operation output
   input [2:0]SELECT;                                          // seletion
   output reg [7:0]RESULT;                                     // output
   always @ ( output_add,output_and,output_or,output_forward,SELECT )
   begin
      case (SELECT)                                // assgin value to result wrt the select
         3'b000  : assign RESULT = output_forward; // forward operation
         3'b001  : assign RESULT = output_add;     // add opertion
         3'b010  : assign RESULT = output_and;     // and  operation
         3'b011  : assign RESULT = output_or;      // or  operation
         default : assign RESULT = 0;
      endcase
   end

endmodule // max8_1
//=========================================================add
module addope(DATA1,DATA2,RESULT);   // modules for add
   input [7:0]DATA1,DATA2;           // data for addition
   output [7:0] RESULT;          // result

   assign #2 RESULT= DATA1+DATA2;        // add two data and assingn to result



endmodule // addoper
//=========================================================and
module andope(DATA1,DATA2,RESULT);    // modules for and
   input [7:0]DATA1,DATA2;            // data for and operation
   output [7:0]RESULT;            // add opertion result
   assign #1 RESULT= DATA1 & DATA2;       // and two data and assingn to result


endmodule // andoper
//=========================================================or
module orope (DATA1,DATA2,RESULT);     // module for or operation
   input [7:0]DATA1,DATA2;             // data for or operation
   output [7:0]RESULT;             // or opertion result
   assign #1 RESULT= DATA1 | DATA2;       // or two data and assingn to result

endmodule // oroper
//=========================================================forward
module forwardope (DATA2,RESULT);     // module for forward opertion
   input [7:0]DATA2;                  // data for forward opertion
   output [7:0]RESULT;            // result of forward operation
   assign #1 RESULT= DATA2;               // change data2 to result

endmodule // forwardoper

Lab 05/part 04/reg.v
//register file
module reg_file(IN,OUT1,OUT2,INADDRESS,OUT1ADDRESS,OUT2ADDRESS, WRITE, CLK, RESET);
   input [7:0] IN;             // 8 bit input to register
   output [7:0] OUT1,OUT2;     // 8 bit output from register
   input [2:0] INADDRESS,OUT1ADDRESS,OUT2ADDRESS;  // 3 bit in and out INADDRESS
   input WRITE,CLK,RESET;      // 1 bit for clk,write and reset
   reg [7:0]regfile[7:0];      // 8 vector of 8 bit register
   integer i;                  // for loop

   always @ (posedge CLK) begin       // change when the clk is positive
      if (RESET)                      // check if rest is 1
         begin
            #1 for(i=0;i<8;i=i+1) begin  //loop  for change the register values as 0
               regfile[i]=0;             // change register values
            end
         end
      end

   always @ (posedge CLK) begin          // write to register syncrnously
         if (WRITE & ~RESET) begin                // when write is enable
            #1 regfile[INADDRESS]= IN;    // chance the ceratin value of the register
         end
      end


   initial
   begin
      #5;
      $display("\n\t\t\t==================================================");
      $display("\t\t\t Change of Register Content Starting from Time #5");
      $display("\t\t\t==================================================\n");
      $display("\t\ttime\treg0\treg1\treg2\treg3\treg4\treg5\treg6\treg7");
      $display("\t\t---------------------------------------------------------------------");
      $monitor($time,"\t%d\t%d\t%d\t%d\t%d\t%d\t%d\t%d",regfile[0],regfile[1],regfile[2],regfile[3],regfile[4],regfile[5],regfile[6],regfile[7]);
   end

   assign #2 OUT1=regfile[OUT1ADDRESS];			//asyncrnously reading from output1
	assign #2 OUT2= regfile[OUT2ADDRESS];        //asyncrnously reading from output2
endmodule

Lab 05/part 04/cpu_tb.v
module test;

   //inputs
    reg clk,reset;
    wire [31:0] inst;
    reg [7:0] memory[1023:0];

    //outputs
    wire [31:0] PC;

  cpu mycpu(PC,inst,clk,reset);
  assign #2 inst={ memory[PC],memory[PC+1],memory[PC+2],memory[PC+3]};   // counter assing




      initial
    begin
//load:000,add:010,sub:011,mov:001,BEQ:111,j:110,  opcode  distina data1   data2
                                                 //11111111222222223333333344444444
{ memory[0],memory[1],memory[2],memory[3]}    =32'b00000000000001000000000000001010;//loadi 4 0x0A
{ memory[4],memory[5],memory[6],memory[7]}    =32'b00000000000001010000000000000001;//loadi 5 0x01
{ memory[8],memory[9],memory[10],memory[11]}  =32'b00000000000001100000000000000001;//loadi 6 0x01
{ memory[12],memory[13],memory[14],memory[15]}=32'b00000000000001110000000000001001;//loadi 7 0x09
{ memory[16],memory[17],memory[18],memory[19]}=32'b00000011000001000000010000000101;//sub 4 4 5
{ memory[20],memory[21],memory[22],memory[23]}=32'b00000111000000010000010000000110;//beq 0x01 4 6
{ memory[24],memory[25],memory[26],memory[27]}=32'b00000110111111010000000000000000;//j 0xFD
{ memory[28],memory[29],memory[30],memory[31]}=32'b00000010000000010000010000000111;//add 1 4 7



        // generate files needed to plot the waveform using GTKWave
        $dumpfile("cpu_wavedata.vcd");
		$dumpvars(0, test);

        clk  = 1'b0;
        reset = 1'b0;

        // TODO: Reset the CPU (by giving a pulse to RESET signal) to start the program execution
         #1
         reset=1'b1;
         #5
        reset = 1'b0;
        // finish simulation after some time
        #400
        $finish;

    end

    // clock signal generation
    always
        #4 clk = ~clk;
    endmodule

Lab 05/part 04/cpu_wavedata.vcd
$date
	Wed Nov 04 14:48:08 2020
$end
$version
	Icarus Verilog
$end
$timescale
	1s
$end
$scope module test $end
$var wire 32 ! inst [31:0] $end
$var wire 32 " PC [31:0] $end
$var reg 1 # clk $end
$var reg 1 $ reset $end
$scope module mycpu $end
$var wire 1 # CLK $end
$var wire 32 % INSTRUCTION [31:0] $end
$var wire 1 & MUX3_SEL $end
$var wire 32 ' PC [31:0] $end
$var wire 1 $ RESET $end
$var wire 3 ( WRITEREG [2:0] $end
$var wire 1 ) zero $end
$var wire 32 * SinEx [31:0] $end
$var wire 3 + READREG2 [2:0] $end
$var wire 3 , READREG1 [2:0] $end
$var wire 8 - OUT5 [7:0] $end
$var wire 8 . OUT4 [7:0] $end
$var wire 8 / OUT3 [7:0] $end
$var wire 8 0 OUT2 [7:0] $end
$var wire 8 1 OUT1 [7:0] $end
$var wire 3 2 OP_CODE [2:0] $end
$var wire 32 3 NEXT [31:0] $end
$var wire 32 4 J_out [31:0] $end
$var wire 8 5 IN [7:0] $end
$var wire 32 6 Branch [31:0] $end
$var wire 32 7 B_out [31:0] $end
$var reg 3 8 ALUOP [2:0] $end
$var reg 1 9 BEQ $end
$var reg 3 : DESTINATION [2:0] $end
$var reg 8 ; IM_VAL [7:0] $end
$var reg 1 < JUMP $end
$var reg 1 = MUX1_SEL $end
$var reg 1 > MUX2_SEL $end
$var reg 1 ? WRITEENABLE $end
$scope module cpu_MUX1 $end
$var wire 1 = control $end
$var wire 8 @ b [7:0] $end
$var wire 8 A a [7:0] $end
$var reg 8 B out [7:0] $end
$upscope $end
$scope module cpu_MUX2 $end
$var wire 8 C a [7:0] $end
$var wire 8 D b [7:0] $end
$var wire 1 > control $end
$var reg 8 E out [7:0] $end
$upscope $end
$scope module cpu_MUX32_1 $end
$var wire 32 F b [31:0] $end
$var wire 1 # clk $end
$var wire 1 & control $end
$var wire 1 $ reset $end
$var wire 32 G a [31:0] $end
$var reg 32 H out [31:0] $end
$upscope $end
$scope module cpu_PC_MUX32 $end
$var wire 1 # clk $end
$var wire 1 < control $end
$var wire 32 I input1 [31:0] $end
$var wire 32 J input2 [31:0] $end
$var wire 1 $ reset $end
$var reg 32 K out [31:0] $end
$upscope $end
$scope module cpu_alu $end
$var wire 8 L DATA2 [7:0] $end
$var wire 3 M SELECT [2:0] $end
$var wire 1 ) ZERO $end
$var wire 8 N output_or [7:0] $end
$var wire 8 O output_forward [7:0] $end
$var wire 8 P output_and [7:0] $end
$var wire 8 Q output_add [7:0] $end
$var wire 8 R RESULT [7:0] $end
$var wire 8 S DATA1 [7:0] $end
$scope module add1 $end
$var wire 8 T DATA2 [7:0] $end
$var wire 8 U RESULT [7:0] $end
$var wire 8 V DATA1 [7:0] $end
$upscope $end
$scope module and1 $end
$var wire 8 W DATA2 [7:0] $end
$var wire 8 X RESULT [7:0] $end
$var wire 8 Y DATA1 [7:0] $end
$upscope $end
$scope module forward1 $end
$var wire 8 Z DATA2 [7:0] $end
$var wire 8 [ RESULT [7:0] $end
$upscope $end
$scope module mux1 $end
$var wire 3 \ SELECT [2:0] $end
$var wire 8 ] output_add [7:0] $end
$var wire 8 ^ output_and [7:0] $end
$var wire 8 _ output_forward [7:0] $end
$var wire 8 ` output_or [7:0] $end
$var reg 8 a RESULT [7:0] $end
$upscope $end
$scope module or1 $end
$var wire 8 b DATA2 [7:0] $end
$var wire 8 c RESULT [7:0] $end
$var wire 8 d DATA1 [7:0] $end
$upscope $end
$upscope $end
$scope module cpu_compliment $end
$var wire 8 e out [7:0] $end
$var wire 8 f in [7:0] $end
$var reg 8 g comp [7:0] $end
$upscope $end
$scope module cpu_counter $end
$var wire 1 # clk $end
$var wire 32 h in_pc [31:0] $end
$var wire 1 $ reset $end
$var reg 32 i out_pc [31:0] $end
$upscope $end
$scope module cpu_reg_file $end
$var wire 1 # CLK $end
$var wire 8 j IN [7:0] $end
$var wire 3 k INADDRESS [2:0] $end
$var wire 8 l OUT1 [7:0] $end
$var wire 3 m OUT1ADDRESS [2:0] $end
$var wire 8 n OUT2 [7:0] $end
$var wire 3 o OUT2ADDRESS [2:0] $end
$var wire 1 $ RESET $end
$var wire 1 ? WRITE $end
$var integer 32 p i [31:0] $end
$upscope $end
$scope module cpu_sing_extend_shift $end
$var wire 8 q IN [7:0] $end
$var wire 32 r OUT [31:0] $end
$var reg 32 s result [31:0] $end
$upscope $end
$upscope $end
$upscope $end
$enddefinitions $end
#0
$dumpvars
bx s
bx r
bx q
bx p
bx o
bx n
bx m
bx l
bx k
bx j
bx i
bx h
b11111111 g
bx f
bx e
bx d
bx c
bx b
bx a
bx `
bx _
bx ^
bx ]
bx \
bx [
bx Z
bx Y
bx X
bx W
bx V
bx U
bx T
bx S
bx R
bx Q
bx P
bx O
bx N
bx M
bx L
bx K
bx J
bx I
bx H
bx G
bx F
bx E
bx D
bx C
bx B
bx A
bx @
x?
x>
x=
x<
bx ;
bx :
x9
bx 8
bx 7
bx 6
bx 5
bx 4
bx 3
bx 2
bx 1
bx 0
bx /
bx .
bx -
bx ,
bx +
bx *
x)
bx (
bx '
x&
bx %
0$
0#
bx "
bx !
$end
#1
b0 7
b0 H
b0 I
1$
#2
b0 "
b0 '
b0 4
b0 K
b0 h
#4
b100 (
b100 k
b100 :
b10 +
b10 o
b0 ,
b0 m
b0 2
b100 3
b100 G
b100 i
b1000000000000001010 !
b1000000000000001010 %
1#
#5
0&
b1010 -
b1010 E
b1010 L
b1010 T
b1010 W
b1010 Z
b1010 b
0<
09
b1010 ;
b1010 C
b1010 q
b0 8
b0 M
b0 \
0>
1?
b1000 p
#6
0)
b0x0x0 P
b0x0x0 X
b0x0x0 ^
bx1x1x N
bx1x1x `
bx1x1x c
b1010 5
b1010 R
b1010 a
b1010 j
b1010 O
b1010 [
b1010 _
0$
#7
b101100 6
b101100 F
b101100 J
b101000 *
b101000 r
b101000 s
b0 0
b0 A
b0 f
b0 n
b0 1
b0 S
b0 V
b0 Y
b0 d
b0 l
#8
b1010 N
b1010 `
b1010 c
b0 P
b0 X
b0 ^
b0 /
b0 @
b0 e
0#
#9
b1010 Q
b1010 U
b1010 ]
#12
b100 7
b100 H
b100 I
1#
#13
b100 "
b100 '
b100 4
b100 K
b100 h
#15
b101 (
b101 k
b101 :
b1 +
b1 o
b1010000000000000001 !
b1010000000000000001 %
#16
b1 -
b1 E
b1 L
b1 T
b1 W
b1 Z
b1 b
b1 ;
b1 C
b1 q
0#
#17
b1 N
b1 `
b1 c
b1 5
b1 R
b1 a
b1 j
b1 O
b1 [
b1 _
#18
b1000 6
b1000 F
b1000 J
b100 *
b100 r
b100 s
b1 Q
b1 U
b1 ]
#20
b1000 7
b1000 H
b1000 I
b1100 6
b1100 F
b1100 J
b1000 3
b1000 G
b1000 i
1#
#21
b1000 "
b1000 '
b1000 4
b1000 K
b1000 h
#23
b110 (
b110 k
b110 :
b1100000000000000001 !
b1100000000000000001 %
#24
0#
#28
b1100 7
b1100 H
b1100 I
b10000 6
b10000 F
b10000 J
b1100 3
b1100 G
b1100 i
1#
#29
b1100 "
b1100 '
b1100 4
b1100 K
b1100 h
#31
b111 (
b111 k
b111 :
b1110000000000001001 !
b1110000000000001001 %
#32
b1001 -
b1001 E
b1001 L
b1001 T
b1001 W
b1001 Z
b1001 b
b1001 ;
b1001 C
b1001 q
0#
#33
b1001 N
b1001 `
b1001 c
b1001 5
b1001 R
b1001 a
b1001 j
b1001 O
b1001 [
b1001 _
#34
b110000 6
b110000 F
b110000 J
b100100 *
b100100 r
b100100 s
b1001 Q
b1001 U
b1001 ]
#36
b10000 7
b10000 H
b10000 I
b110100 6
b110100 F
b110100 J
b10000 3
b10000 G
b10000 i
1#
#37
b10000 "
b10000 '
b10000 4
b10000 K
b10000 h
#39
b100 (
b100 k
b100 :
b101 +
b101 o
b100 ,
b100 m
b11 2
b11000001000000010000000101 !
b11000001000000010000000101 %
#40
b0 -
b0 E
b0 L
b0 T
b0 W
b0 Z
b0 b
b0 .
b0 B
b0 D
b0 ;
b0 C
b0 q
b1 8
b1 M
b1 \
1>
1=
0#
#41
b0 N
b0 `
b0 c
b0 O
b0 [
b0 _
b1 0
b1 A
b1 f
b1 n
b1010 1
b1010 S
b1010 V
b1010 Y
b1010 d
b1010 l
#42
b10000 6
b10000 F
b10000 J
b0 *
b0 r
b0 s
b11111111 -
b11111111 E
b11111111 L
b11111111 T
b11111111 W
b11111111 Z
b11111111 b
b11111111 .
b11111111 B
b11111111 D
b1010 N
b1010 `
b1010 c
b11111111 /
b11111111 @
b11111111 e
#43
b1010 P
b1010 X
b1010 ^
b11111111 N
b11111111 `
b11111111 c
b11111111 O
b11111111 [
b11111111 _
#44
b10100 7
b10100 H
b10100 I
b10100 6
b10100 F
b10100 J
b10100 3
b10100 G
b10100 i
1#
#45
b10100 "
b10100 '
b10100 4
b10100 K
b10100 h
#47
b1 (
b1 k
b1 :
b110 +
b110 o
b111 2
b111000000010000010000000110 !
b111000000010000010000000110 %
b1001 1
b1001 S
b1001 V
b1001 Y
b1001 d
b1001 l
#48
b1001 P
b1001 X
b1001 ^
0#
#49
b1 ;
b1 C
b1 q
19
0?
b1000 5
b1000 R
b1000 a
b1000 j
b1000 Q
b1000 U
b1000 ]
#51
b11000 6
b11000 F
b11000 J
b100 *
b100 r
b100 s
#52
b11000 7
b11000 H
b11000 I
b11100 6
b11100 F
b11100 J
b11000 3
b11000 G
b11000 i
1#
#53
b11000 "
b11000 '
b11000 4
b11000 K
b11000 h
#55
b101 (
b101 k
b101 :
b0 +
b0 o
b0 ,
b0 m
b110 2
b110111111010000000000000000 !
b110111111010000000000000000 %
#56
0#
#57
b11111101 ;
b11111101 C
b11111101 q
1<
09
b0 0
b0 A
b0 f
b0 n
b0 1
b0 S
b0 V
b0 Y
b0 d
b0 l
#58
b0 -
b0 E
b0 L
b0 T
b0 W
b0 Z
b0 b
b0 .
b0 B
b0 D
b0 P
b0 X
b0 ^
b0 /
b0 @
b0 e
#59
b1100 6
b1100 F
b1100 J
b11111111111111111111111111110100 *
b11111111111111111111111111110100 r
b11111111111111111111111111110100 s
b0 N
b0 `
b0 c
b0 O
b0 [
b0 _
#60
1)
b11100 7
b11100 H
b11100 I
b10000 6
b10000 F
b10000 J
b11100 3
b11100 G
b11100 i
b0 5
b0 R
b0 a
b0 j
b0 Q
b0 U
b0 ]
1#
#61
b10000 "
b10000 '
b10000 4
b10000 K
b10000 h
#63
b100 (
b100 k
b100 :
b101 +
b101 o
b100 ,
b100 m
b11 2
b11000001000000010000000101 !
b11000001000000010000000101 %
#64
b0 ;
b0 C
b0 q
0<
1?
0#
#65
b1 0
b1 A
b1 f
b1 n
b1001 1
b1001 S
b1001 V
b1001 Y
b1001 d
b1001 l
#66
b11100 6
b11100 F
b11100 J
b0 *
b0 r
b0 s
b11111111 -
b11111111 E
b11111111 L
b11111111 T
b11111111 W
b11111111 Z
b11111111 b
b11111111 .
b11111111 B
b11111111 D
b1001 N
b1001 `
b1001 c
b11111111 /
b11111111 @
b11111111 e
#67
b1001 P
b1001 X
b1001 ^
b11111111 N
b11111111 `
b11111111 c
b11111111 O
b11111111 [
b11111111 _
#68
0)
b10100 7
b10100 H
b10100 I
b10100 6
b10100 F
b10100 J
b10100 3
b10100 G
b10100 i
b1000 5
b1000 R
b1000 a
b1000 j
b1000 Q
b1000 U
b1000 ]
1#
#69
b10100 "
b10100 '
b10100 4
b10100 K
b10100 h
#71
b1 (
b1 k
b1 :
b110 +
b110 o
b111 2
b111000000010000010000000110 !
b111000000010000010000000110 %
b1000 1
b1000 S
b1000 V
b1000 Y
b1000 d
b1000 l
#72
b1000 P
b1000 X
b1000 ^
0#
#73
b1 ;
b1 C
b1 q
19
0?
b111 5
b111 R
b111 a
b111 j
b111 Q
b111 U
b111 ]
#75
b11000 6
b11000 F
b11000 J
b100 *
b100 r
b100 s
#76
b11000 7
b11000 H
b11000 I
b11100 6
b11100 F
b11100 J
b11000 3
b11000 G
b11000 i
1#
#77
b11000 "
b11000 '
b11000 4
b11000 K
b11000 h
#79
b101 (
b101 k
b101 :
b0 +
b0 o
b0 ,
b0 m
b110 2
b110111111010000000000000000 !
b110111111010000000000000000 %
#80
0#
#81
b11111101 ;
b11111101 C
b11111101 q
1<
09
b0 0
b0 A
b0 f
b0 n
b0 1
b0 S
b0 V
b0 Y
b0 d
b0 l
#82
b0 -
b0 E
b0 L
b0 T
b0 W
b0 Z
b0 b
b0 .
b0 B
b0 D
b0 P
b0 X
b0 ^
b0 /
b0 @
b0 e
#83
b1100 6
b1100 F
b1100 J
b11111111111111111111111111110100 *
b11111111111111111111111111110100 r
b11111111111111111111111111110100 s
b0 N
b0 `
b0 c
b0 O
b0 [
b0 _
#84
1)
b11100 7
b11100 H
b11100 I
b10000 6
b10000 F
b10000 J
b11100 3
b11100 G
b11100 i
b0 5
b0 R
b0 a
b0 j
b0 Q
b0 U
b0 ]
1#
#85
b10000 "
b10000 '
b10000 4
b10000 K
b10000 h
#87
b100 (
b100 k
b100 :
b101 +
b101 o
b100 ,
b100 m
b11 2
b11000001000000010000000101 !
b11000001000000010000000101 %
#88
b0 ;
b0 C
b0 q
0<
1?
0#
#89
b1 0
b1 A
b1 f
b1 n
b1000 1
b1000 S
b1000 V
b1000 Y
b1000 d
b1000 l
#90
b11100 6
b11100 F
b11100 J
b0 *
b0 r
b0 s
b11111111 -
b11111111 E
b11111111 L
b11111111 T
b11111111 W
b11111111 Z
b11111111 b
b11111111 .
b11111111 B
b11111111 D
b1000 N
b1000 `
b1000 c
b11111111 /
b11111111 @
b11111111 e
#91
b1000 P
b1000 X
b1000 ^
b11111111 N
b11111111 `
b11111111 c
b11111111 O
b11111111 [
b11111111 _
#92
0)
b10100 7
b10100 H
b10100 I
b10100 6
b10100 F
b10100 J
b10100 3
b10100 G
b10100 i
b111 5
b111 R
b111 a
b111 j
b111 Q
b111 U
b111 ]
1#
#93
b10100 "
b10100 '
b10100 4
b10100 K
b10100 h
#95
b1 (
b1 k
b1 :
b110 +
b110 o
b111 2
b111000000010000010000000110 !
b111000000010000010000000110 %
b111 1
b111 S
b111 V
b111 Y
b111 d
b111 l
#96
b111 P
b111 X
b111 ^
0#
#97
b1 ;
b1 C
b1 q
19
0?
b110 5
b110 R
b110 a
b110 j
b110 Q
b110 U
b110 ]
#99
b11000 6
b11000 F
b11000 J
b100 *
b100 r
b100 s
#100
b11000 7
b11000 H
b11000 I
b11100 6
b11100 F
b11100 J
b11000 3
b11000 G
b11000 i
1#
#101
b11000 "
b11000 '
b11000 4
b11000 K
b11000 h
#103
b101 (
b101 k
b101 :
b0 +
b0 o
b0 ,
b0 m
b110 2
b110111111010000000000000000 !
b110111111010000000000000000 %
#104
0#
#105
b11111101 ;
b11111101 C
b11111101 q
1<
09
b0 0
b0 A
b0 f
b0 n
b0 1
b0 S
b0 V
b0 Y
b0 d
b0 l
#106
b0 -
b0 E
b0 L
b0 T
b0 W
b0 Z
b0 b
b0 .
b0 B
b0 D
b0 P
b0 X
b0 ^
b0 /
b0 @
b0 e
#107
b1100 6
b1100 F
b1100 J
b11111111111111111111111111110100 *
b11111111111111111111111111110100 r
b11111111111111111111111111110100 s
b0 N
b0 `
b0 c
b0 O
b0 [
b0 _
#108
1)
b11100 7
b11100 H
b11100 I
b10000 6
b10000 F
b10000 J
b11100 3
b11100 G
b11100 i
b0 5
b0 R
b0 a
b0 j
b0 Q
b0 U
b0 ]
1#
#109
b10000 "
b10000 '
b10000 4
b10000 K
b10000 h
#111
b100 (
b100 k
b100 :
b101 +
b101 o
b100 ,
b100 m
b11 2
b11000001000000010000000101 !
b11000001000000010000000101 %
#112
b0 ;
b0 C
b0 q
0<
1?
0#
#113
b1 0
b1 A
b1 f
b1 n
b111 1
b111 S
b111 V
b111 Y
b111 d
b111 l
#114
b11100 6
b11100 F
b11100 J
b0 *
b0 r
b0 s
b11111111 -
b11111111 E
b11111111 L
b11111111 T
b11111111 W
b11111111 Z
b11111111 b
b11111111 .
b11111111 B
b11111111 D
b111 N
b111 `
b111 c
b11111111 /
b11111111 @
b11111111 e
#115
b111 P
b111 X
b111 ^
b11111111 N
b11111111 `
b11111111 c
b11111111 O
b11111111 [
b11111111 _
